coinbase_agentkit_langchain/__init__.py
coinbase_agentkit_langchain/langchain_tools.py
coinbase_agentkit_langchain-0.7.0.dist-info/METADATA
coinbase_agentkit_langchain-0.7.0.dist-info/WHEEL
coinbase_agentkit_langchain-0.7.0.dist-info/RECORD
