Metadata-Version: 2.4
Name: coinbase-agentkit-langchain
Version: 0.7.0
Summary: Coinbase AgentKit LangChain extension
Author-email: John Peterson <john.peterson@coinbase.com>
License-Expression: Apache-2.0
Keywords: agent,agentkit,ai,cdp,coinbase,crypto,langchain,sdk
Requires-Python: ~=3.10
Requires-Dist: coinbase-agentkit<0.8,>=0.7.2
Requires-Dist: langchain<0.4,>=0.3.4
Requires-Dist: nest-asyncio<2,>=1.5.8
Requires-Dist: python-dotenv<2,>=1.0.1
